neo_tls_client/__init__.py
neo_tls_client/__version__.py
neo_tls_client/cffi.py
neo_tls_client/cookies.py
neo_tls_client/exceptions.py
neo_tls_client/response.py
neo_tls_client/sessions.py
neo_tls_client/settings.py
neo_tls_client/structures.py
neo_tls_client/dependencies/__init__.py
neo_tls_client/dependencies/tls-client-darwin-amd64-1.7.9.dylib
neo_tls_client/dependencies/tls-client-darwin-arm64-1.7.9.dylib
neo_tls_client/dependencies/tls-client-linux-amd64-1.7.9.so
neo_tls_client/dependencies/tls-client-linux-arm64-1.7.9.so
neo_tls_client/dependencies/tls-client-windows-32-1.7.9.dll
neo_tls_client/dependencies/tls-client-windows-64-1.7.9.dll
neo_tls_client-1.0.2.dist-info/LICENSE
neo_tls_client-1.0.2.dist-info/METADATA
neo_tls_client-1.0.2.dist-info/WHEEL
neo_tls_client-1.0.2.dist-info/top_level.txt
neo_tls_client-1.0.2.dist-info/RECORD
